fh_appconf/__about__.py
fh_appconf/__init__.py
fh_appconf/files.py
fh_appconf/settings.py
fh_appconf/validation.py
fh_appconf-0.1.1.dist-info/METADATA
fh_appconf-0.1.1.dist-info/WHEEL
fh_appconf-0.1.1.dist-info/licenses/LICENSE.txt
fh_appconf-0.1.1.dist-info/RECORD
